lmfitxps/__init__.py
lmfitxps/backgrounds.py
lmfitxps/lineshapes.py
lmfitxps/models.py
lmfitxps-4.2.0.dist-info/licenses/LICENSE
lmfitxps-4.2.0.dist-info/METADATA
lmfitxps-4.2.0.dist-info/WHEEL
lmfitxps-4.2.0.dist-info/top_level.txt
lmfitxps-4.2.0.dist-info/RECORD
