Metadata-Version: 2.4
Name: lmfitxps
Version: 4.2.0
Summary: This package contains additional models for the lmfit package for fitting XPS spectra.
Author-email: Julian Hochhaus <julian.hochhaus@tu-dortmund.de>
License: MIT License
Project-URL: homepage, https://github.com/Julian-Hochhaus/lmfitxps
Project-URL: documentation, https://lmfitxps.readthedocs.io/en/latest/
License-File: LICENSE
Dynamic: license-file
